telegram_me/__init__.py
telegram_me/username.py
telegram_me-1.0.1.dist-info/DESCRIPTION.rst
telegram_me-1.0.1.dist-info/METADATA
telegram_me-1.0.1.dist-info/RECORD
telegram_me-1.0.1.dist-info/WHEEL
telegram_me-1.0.1.dist-info/metadata.json
telegram_me-1.0.1.dist-info/top_level.txt
