Metadata-Version: 2.0
Name: telegram-me
Version: 1.0.1
Summary: A simple scraper for getting information from t.me links
Home-page: https://github.com/hearot/telegram_me
Author: Hearot
Author-email: gabriel@hearot.it
License: MIT
Project-URL: Tracker, https://github.com/hearot/telegram_me/issues
Project-URL: Source, https://github.com/hearot/telegram_me
Keywords: bot bots chat messenger mtproto python telegram telegram_me me telegramme scraping
Platform: UNKNOWN
Classifier: Development Status :: 5 - Production/Stable
Classifier: Intended Audience :: Developers
Classifier: License :: OSI Approved :: MIT License
Classifier: Natural Language :: English
Classifier: Operating System :: OS Independent
Classifier: Programming Language :: Python
Classifier: Programming Language :: Python :: 3
Classifier: Programming Language :: Python :: 3.6
Classifier: Programming Language :: Python :: 3.7
Classifier: Programming Language :: Python :: 3.8
Classifier: Programming Language :: Python :: Implementation
Classifier: Programming Language :: Python :: Implementation :: CPython
Classifier: Programming Language :: Python :: Implementation :: PyPy
Classifier: Topic :: Communications
Classifier: Topic :: Communications :: Chat
Classifier: Topic :: Internet
Classifier: Topic :: Software Development :: Libraries
Classifier: Topic :: Software Development :: Libraries :: Application Frameworks
Classifier: Topic :: Software Development :: Libraries :: Python Modules
Classifier: Typing :: Typed
Requires-Python: >=3.6.*
Requires-Dist: attrs
Requires-Dist: lxml
Requires-Dist: requests
